{
  "programId": "G6dU3Ghhg7YGkSttucjvRzErkMAgPhFHx3efZ65Embin",
  "stateAddress": "FAjhJ4GL3mcTX5w6NV5mEBBgSNFJRoPf7Si6GNXLqS8n",
  "statePrivateKey": [
    170,
    133,
    223,
    211,
    65,
    11,
    242,
    72,
    222,
    25,
    233,
    75,
    74,
    120,
    58,
    107,
    9,
    44,
    243,
    79,
    214,
    234,
    220,
    196,
    83,
    43,
    156,
    240,
    146,
    240,
    245,
    55,
    210,
    130,
    30,
    140,
    114,
    35,
    164,
    0,
    198,
    241,
    138,
    191,
    242,
    251,
    43,
    250,
    22,
    72,
    179,
    144,
    143,
    37,
    141,
    44,
    9,
    140,
    51,
    160,
    193,
    75,
    182,
    119
  ],
  "programSolVault": "4DukmB9FrBNFRUzJcTXWbEWbbigKH4Hg9XBSAEaXAn5T",
  "programSolVaultBump": 249,
  "ownerWallet": "QgNN4aW9hPz4ANP1LqzR2FkDPZo9MzDZxDQ4abovHYv",
  "multisigTreasury": "5C16cVYXe7KRPz6rBD33qhcqyjvy42LP8tyJRNMXbKiL",
  "version": "no-mint-swap-only",
  "hasReentrancyProtection": true,
  "contractVersion": "swap-only-v1.0"
}